google/cloud/storage/__init__.py
google/cloud/storage/_helpers.py
google/cloud/storage/_http.py
google/cloud/storage/_opentelemetry_tracing.py
google/cloud/storage/_signing.py
google/cloud/storage/acl.py
google/cloud/storage/batch.py
google/cloud/storage/blob.py
google/cloud/storage/bucket.py
google/cloud/storage/client.py
google/cloud/storage/constants.py
google/cloud/storage/fileio.py
google/cloud/storage/hmac_key.py
google/cloud/storage/iam.py
google/cloud/storage/notification.py
google/cloud/storage/retry.py
google/cloud/storage/transfer_manager.py
google/cloud/storage/version.py
google_cloud_storage-2.18.1.dist-info/LICENSE
google_cloud_storage-2.18.1.dist-info/METADATA
google_cloud_storage-2.18.1.dist-info/WHEEL
google_cloud_storage-2.18.1.dist-info/top_level.txt
google_cloud_storage-2.18.1.dist-info/RECORD
