Metadata-Version: 2.1
Name: google-cloud-storage
Version: 2.18.1
Summary: Google Cloud Storage API client library
Home-page: https://github.com/googleapis/python-storage
Author: Google LLC
Author-email: googleapis-packages@google.com
License: Apache 2.0
Platform: Posix; MacOS X; Windows
Classifier: Development Status :: 5 - Production/Stable
Classifier: Intended Audience :: Developers
Classifier: License :: OSI Approved :: Apache Software License
Classifier: Programming Language :: Python
Classifier: Programming Language :: Python :: 3
Classifier: Programming Language :: Python :: 3.7
Classifier: Programming Language :: Python :: 3.8
Classifier: Programming Language :: Python :: 3.9
Classifier: Programming Language :: Python :: 3.10
Classifier: Programming Language :: Python :: 3.11
Classifier: Programming Language :: Python :: 3.12
Classifier: Operating System :: OS Independent
Classifier: Topic :: Internet
Requires-Python: >=3.7
License-File: LICENSE
Requires-Dist: google-auth<3.0dev,>=2.26.1
Requires-Dist: google-api-core<3.0.0dev,>=2.15.0
Requires-Dist: google-cloud-core<3.0dev,>=2.3.0
Requires-Dist: google-resumable-media>=2.6.0
Requires-Dist: requests<3.0.0dev,>=2.18.0
Requires-Dist: google-crc32c<2.0dev,>=1.0
Provides-Extra: protobuf
Requires-Dist: protobuf<6.0.0dev; extra == "protobuf"
Provides-Extra: tracing
Requires-Dist: opentelemetry-api>=1.1.0; extra == "tracing"
